__init__.py
main.py
contacts_assistant/Email.py
contacts_assistant/__init__.py
contacts_assistant/address.py
contacts_assistant/birthday.py
contacts_assistant/command_completer.py
contacts_assistant/constants.py
contacts_assistant/contact_email.py
contacts_assistant/contacts_book.py
contacts_assistant/date_helpers.py
contacts_assistant/field.py
contacts_assistant/handler.py
contacts_assistant/main.py
contacts_assistant/menu.py
contacts_assistant/name.py
contacts_assistant/note.py
contacts_assistant/notebook.py
contacts_assistant/phone.py
contacts_assistant/record.py
contacts_assistant/utils.py
contacts_assistant-0.0.14.dist-info/LICENSE
contacts_assistant-0.0.14.dist-info/METADATA
contacts_assistant-0.0.14.dist-info/WHEEL
contacts_assistant-0.0.14.dist-info/entry_points.txt
contacts_assistant-0.0.14.dist-info/top_level.txt
contacts_assistant-0.0.14.dist-info/RECORD
