Metadata-Version: 2.1
Name: contacts_assistant
Version: 0.0.14
Summary: Contacts Assistant is a bot designed to help you manage your address book efficiently. Below is a list of available commands, their functions, and required arguments. Additionally, you can add your notes to our notebook.
Home-page: https://github.com/Bignichok/Python-ContactsAssistant
Author: Mykyta Samoilenko
Author-email: inikita546@gmail.com
Classifier: Programming Language :: Python :: 3
Classifier: License :: OSI Approved :: MIT License
Classifier: Operating System :: OS Independent
Requires-Python: >=3.8
License-File: LICENSE
Requires-Dist: colorama ==0.4.6
Requires-Dist: prompt-toolkit ==3.0.43
Requires-Dist: wcwidth ==0.2.13
